remix/framework/__init__.py
remix/framework/api/__init__.py
remix/framework/api/dataset.py
remix/framework/api/instance.py
remix/framework/api/run.py
remix/framework/api/test.py
remix/framework/api/transform.py
remix/framework/backend/__init__.py
remix/framework/backend/excel.py
remix/framework/backend/polars.py
remix/framework/cli/__init__.py
remix/framework/cli/build_schemas.py
remix/framework/cli/main.py
remix/framework/cli/run.py
remix/framework/cli/test.py
remix/framework/cli/transform.py
remix/framework/model/run_remix.gms
remix/framework/model/source/accounting/annuities.gms
remix/framework/model/source/accounting/equations.gms
remix/framework/model/source/accounting/inc_acclinks.gms
remix/framework/model/source/accounting/inc_accnodes.gms
remix/framework/model/source/accounting/input.gms
remix/framework/model/source/battools/aggregateAccountingMean.gms
remix/framework/model/source/battools/aggregateNodes.gms
remix/framework/model/source/core/balance.gms
remix/framework/model/source/core/converter.gms
remix/framework/model/source/core/sourcesink.gms
remix/framework/model/source/core/storage.gms
remix/framework/model/source/core/transfer.gms
remix/framework/model/source/data_inheritance.gms
remix/framework/model/source/loadgdx.gms
remix/framework/model/source/metadata.gms
remix/framework/model/source/methods/checkanno.gms
remix/framework/model/source/methods/iternodes.gms
remix/framework/model/source/methods/mga.gms
remix/framework/model/source/methods/mga_pre.gms
remix/framework/model/source/methods/pareto.gms
remix/framework/model/source/methods/pareto_pre.gms
remix/framework/model/source/methods/pips.gms
remix/framework/model/source/methods/solve.gms
remix/framework/model/source/methods/test_inputdata.gms
remix/framework/model/source/model_properties.gms
remix/framework/model/source/optiframe.gms
remix/framework/model/source/postcalc/declaration.gms
remix/framework/model/source/postcalc/definition.gms
remix/framework/model/source/postcalc/writegdx.gms
remix_framework-0.14.0.dist-info/WHEEL
remix_framework-0.14.0.dist-info/entry_points.txt
remix_framework-0.14.0.dist-info/METADATA
remix_framework-0.14.0.dist-info/RECORD
