Metadata-Version: 2.3
Name: remix.framework
Version: 0.14.0
Keywords: 
Author: REMix Developers
Author-email: REMix Developers <remix@dlr.de>
License: BSD 3-Clause License
Classifier: Development Status :: 5 - Production/Stable
Classifier: Intended Audience :: Science/Research
Classifier: License :: OSI Approved :: BSD License
Classifier: Operating System :: Microsoft :: Windows
Classifier: Operating System :: POSIX
Classifier: Operating System :: Unix
Classifier: Programming Language :: Python
Classifier: Programming Language :: Python :: 3 :: Only
Classifier: Programming Language :: Python :: 3.9
Classifier: Programming Language :: Python :: 3.10
Classifier: Programming Language :: Python :: 3.11
Classifier: Programming Language :: Python :: 3.12
Classifier: Programming Language :: Python :: 3.13
Classifier: Topic :: Scientific/Engineering
Requires-Dist: jsonschema
Requires-Dist: networkx
Requires-Dist: numpy
Requires-Dist: pandas
Requires-Dist: polars
Requires-Dist: pyyaml
Requires-Dist: requests
Requires-Dist: typer
Requires-Dist: gamsapi
Requires-Dist: remix-framework[dev] ; extra == 'all'
Requires-Dist: remix-framework[plotting] ; extra == 'all'
Requires-Dist: remix-framework[docs] ; extra == 'all'
Requires-Dist: remix-framework[plotting] ; extra == 'dev'
Requires-Dist: coverage ; extra == 'dev'
Requires-Dist: pytest ; extra == 'dev'
Requires-Dist: pytest-cov ; extra == 'dev'
Requires-Dist: remix-framework[plotting] ; extra == 'docs'
Requires-Dist: jupytext ; extra == 'docs'
Requires-Dist: myst-parser ; extra == 'docs'
Requires-Dist: nbconvert ; extra == 'docs'
Requires-Dist: pandoc ; extra == 'docs'
Requires-Dist: pydata-sphinx-theme<=0.10.1 ; extra == 'docs'
Requires-Dist: sphinx<7 ; extra == 'docs'
Requires-Dist: sphinx-autobuild ; extra == 'docs'
Requires-Dist: sphinx-copybutton ; extra == 'docs'
Requires-Dist: sphinxcontrib-jquery ; extra == 'docs'
Requires-Dist: sphinx-design ; extra == 'docs'
Requires-Dist: sphinxcontrib-bibtex ; extra == 'docs'
Requires-Dist: sphinx-multiversion ; extra == 'docs'
Requires-Dist: openpyxl ; extra == 'excel'
Requires-Dist: cartopy ; extra == 'plotting'
Requires-Dist: fiona ; extra == 'plotting'
Requires-Dist: shapely ; extra == 'plotting'
Requires-Dist: ipykernel ; extra == 'plotting'
Requires-Dist: matplotlib ; extra == 'plotting'
Requires-Dist: remix-framework[plotting] ; extra == 'tutorials'
Requires-Python: >=3.9
Project-URL: Changelog, https://gitlab.com/dlr-ve/esy/remix/framework/-/releases
Project-URL: Documentation, https://dlr-ve.gitlab.io/esy/remix/framework/
Project-URL: Homepage, https://gitlab.com/dlr-ve/esy/remix/framework
Project-URL: Repository, https://gitlab.com/dlr-ve/esy/remix/framework.git
Provides-Extra: all
Provides-Extra: dev
Provides-Extra: docs
Provides-Extra: excel
Provides-Extra: plotting
Provides-Extra: tutorials
